SNMatOperations/__init__.py
SNMatOperations/input_matrix.py
SNMatOperations/mat_addition.py
SNMatOperations/mat_multiplication.py
SNMatOperations/mat_subraction.py
SNMatrixOperations-0.1.dist-info/LICENCE.txt
SNMatrixOperations-0.1.dist-info/METADATA
SNMatrixOperations-0.1.dist-info/WHEEL
SNMatrixOperations-0.1.dist-info/top_level.txt
SNMatrixOperations-0.1.dist-info/RECORD
